{
  "id": "b2db49c1-f335-4bf0-9f99-5a6c6f9ac3af",
  "prevId": "00000000-0000-0000-0000-000000000000",
  "version": "7",
  "dialect": "postgresql",
  "tables": {
    "public.orders": {
      "name": "orders",
      "schema": "",
      "columns": {
        "id": {
          "name": "id",
          "type": "serial",
          "primaryKey": true,
          "notNull": true
        },
        "broker_name": {
          "name": "broker_name",
          "type": "text",
          "primaryKey": false,
          "notNull": true
        },
        "insured_name": {
          "name": "insured_name",
          "type": "text",
          "primaryKey": false,
          "notNull": true
        },
        "marine_product_type": {
          "name": "marine_product_type",
          "type": "text",
          "primaryKey": false,
          "notNull": true
        },
        "business_type": {
          "name": "business_type",
          "type": "text",
          "primaryKey": false,
          "notNull": true
        },
        "premium": {
          "name": "premium",
          "type": "numeric",
          "primaryKey": false,
          "notNull": true
        },
        "currency": {
          "name": "currency",
          "type": "text",
          "primaryKey": false,
          "notNull": true
        },
        "order_date": {
          "name": "order_date",
          "type": "timestamp",
          "primaryKey": false,
          "notNull": true
        },
        "statuses": {
          "name": "statuses",
          "type": "text[]",
          "primaryKey": false,
          "notNull": true
        },
        "notes": {
          "name": "notes",
          "type": "text",
          "primaryKey": false,
          "notNull": false
        },
        "requires_pre_condition_survey": {
          "name": "requires_pre_condition_survey",
          "type": "boolean",
          "primaryKey": false,
          "notNull": true,
          "default": false
        },
        "created_by": {
          "name": "created_by",
          "type": "serial",
          "primaryKey": false,
          "notNull": true
        },
        "last_updated": {
          "name": "last_updated",
          "type": "timestamp",
          "primaryKey": false,
          "notNull": true
        }
      },
      "indexes": {},
      "foreignKeys": {
        "orders_created_by_users_id_fk": {
          "name": "orders_created_by_users_id_fk",
          "tableFrom": "orders",
          "tableTo": "users",
          "columnsFrom": [
            "created_by"
          ],
          "columnsTo": [
            "id"
          ],
          "onDelete": "no action",
          "onUpdate": "no action"
        }
      },
      "compositePrimaryKeys": {},
      "uniqueConstraints": {},
      "policies": {},
      "checkConstraints": {},
      "isRLSEnabled": false
    },
    "public.property_engineering_orders": {
      "name": "property_engineering_orders",
      "schema": "",
      "columns": {
        "id": {
          "name": "id",
          "type": "serial",
          "primaryKey": true,
          "notNull": true
        },
        "broker_name": {
          "name": "broker_name",
          "type": "text",
          "primaryKey": false,
          "notNull": true
        },
        "insured_name": {
          "name": "insured_name",
          "type": "text",
          "primaryKey": false,
          "notNull": true
        },
        "product_type": {
          "name": "product_type",
          "type": "text",
          "primaryKey": false,
          "notNull": true
        },
        "cover_group": {
          "name": "cover_group",
          "type": "text",
          "primaryKey": false,
          "notNull": true
        },
        "business_type": {
          "name": "business_type",
          "type": "text",
          "primaryKey": false,
          "notNull": true
        },
        "premium": {
          "name": "premium",
          "type": "numeric",
          "primaryKey": false,
          "notNull": true
        },
        "currency": {
          "name": "currency",
          "type": "text",
          "primaryKey": false,
          "notNull": true
        },
        "order_date": {
          "name": "order_date",
          "type": "timestamp",
          "primaryKey": false,
          "notNull": true
        },
        "statuses": {
          "name": "statuses",
          "type": "text[]",
          "primaryKey": false,
          "notNull": true
        },
        "notes": {
          "name": "notes",
          "type": "text",
          "primaryKey": false,
          "notNull": false
        },
        "requires_pre_condition_survey": {
          "name": "requires_pre_condition_survey",
          "type": "boolean",
          "primaryKey": false,
          "notNull": true,
          "default": false
        },
        "created_by": {
          "name": "created_by",
          "type": "serial",
          "primaryKey": false,
          "notNull": true
        },
        "last_updated": {
          "name": "last_updated",
          "type": "timestamp",
          "primaryKey": false,
          "notNull": true
        }
      },
      "indexes": {},
      "foreignKeys": {
        "property_engineering_orders_created_by_users_id_fk": {
          "name": "property_engineering_orders_created_by_users_id_fk",
          "tableFrom": "property_engineering_orders",
          "tableTo": "users",
          "columnsFrom": [
            "created_by"
          ],
          "columnsTo": [
            "id"
          ],
          "onDelete": "no action",
          "onUpdate": "no action"
        }
      },
      "compositePrimaryKeys": {},
      "uniqueConstraints": {},
      "policies": {},
      "checkConstraints": {},
      "isRLSEnabled": false
    },
    "public.property_engineering_quotations": {
      "name": "property_engineering_quotations",
      "schema": "",
      "columns": {
        "id": {
          "name": "id",
          "type": "serial",
          "primaryKey": true,
          "notNull": true
        },
        "broker_name": {
          "name": "broker_name",
          "type": "text",
          "primaryKey": false,
          "notNull": true
        },
        "insured_name": {
          "name": "insured_name",
          "type": "text",
          "primaryKey": false,
          "notNull": true
        },
        "product_type": {
          "name": "product_type",
          "type": "text",
          "primaryKey": false,
          "notNull": true
        },
        "cover_group": {
          "name": "cover_group",
          "type": "text",
          "primaryKey": false,
          "notNull": true
        },
        "estimated_premium": {
          "name": "estimated_premium",
          "type": "numeric",
          "primaryKey": false,
          "notNull": true
        },
        "currency": {
          "name": "currency",
          "type": "text",
          "primaryKey": false,
          "notNull": true
        },
        "quotation_date": {
          "name": "quotation_date",
          "type": "timestamp",
          "primaryKey": false,
          "notNull": true
        },
        "status": {
          "name": "status",
          "type": "text",
          "primaryKey": false,
          "notNull": true
        },
        "decline_reason": {
          "name": "decline_reason",
          "type": "text",
          "primaryKey": false,
          "notNull": false
        },
        "notes": {
          "name": "notes",
          "type": "text",
          "primaryKey": false,
          "notNull": false
        },
        "requires_pre_condition_survey": {
          "name": "requires_pre_condition_survey",
          "type": "boolean",
          "primaryKey": false,
          "notNull": true,
          "default": false
        },
        "created_by": {
          "name": "created_by",
          "type": "serial",
          "primaryKey": false,
          "notNull": true
        },
        "last_updated": {
          "name": "last_updated",
          "type": "timestamp",
          "primaryKey": false,
          "notNull": true
        }
      },
      "indexes": {},
      "foreignKeys": {
        "property_engineering_quotations_created_by_users_id_fk": {
          "name": "property_engineering_quotations_created_by_users_id_fk",
          "tableFrom": "property_engineering_quotations",
          "tableTo": "users",
          "columnsFrom": [
            "created_by"
          ],
          "columnsTo": [
            "id"
          ],
          "onDelete": "no action",
          "onUpdate": "no action"
        }
      },
      "compositePrimaryKeys": {},
      "uniqueConstraints": {},
      "policies": {},
      "checkConstraints": {},
      "isRLSEnabled": false
    },
    "public.property_engineering_status_logs": {
      "name": "property_engineering_status_logs",
      "schema": "",
      "columns": {
        "id": {
          "name": "id",
          "type": "serial",
          "primaryKey": true,
          "notNull": true
        },
        "order_id": {
          "name": "order_id",
          "type": "serial",
          "primaryKey": false,
          "notNull": true
        },
        "statuses": {
          "name": "statuses",
          "type": "text[]",
          "primaryKey": false,
          "notNull": true
        },
        "timestamp": {
          "name": "timestamp",
          "type": "timestamp",
          "primaryKey": false,
          "notNull": true
        },
        "notes": {
          "name": "notes",
          "type": "text",
          "primaryKey": false,
          "notNull": false
        }
      },
      "indexes": {},
      "foreignKeys": {
        "property_engineering_status_logs_order_id_property_engineering_orders_id_fk": {
          "name": "property_engineering_status_logs_order_id_property_engineering_orders_id_fk",
          "tableFrom": "property_engineering_status_logs",
          "tableTo": "property_engineering_orders",
          "columnsFrom": [
            "order_id"
          ],
          "columnsTo": [
            "id"
          ],
          "onDelete": "no action",
          "onUpdate": "no action"
        }
      },
      "compositePrimaryKeys": {},
      "uniqueConstraints": {},
      "policies": {},
      "checkConstraints": {},
      "isRLSEnabled": false
    },
    "public.quotations": {
      "name": "quotations",
      "schema": "",
      "columns": {
        "id": {
          "name": "id",
          "type": "serial",
          "primaryKey": true,
          "notNull": true
        },
        "broker_name": {
          "name": "broker_name",
          "type": "text",
          "primaryKey": false,
          "notNull": true
        },
        "insured_name": {
          "name": "insured_name",
          "type": "text",
          "primaryKey": false,
          "notNull": true
        },
        "marine_product_type": {
          "name": "marine_product_type",
          "type": "text",
          "primaryKey": false,
          "notNull": true
        },
        "estimated_premium": {
          "name": "estimated_premium",
          "type": "numeric",
          "primaryKey": false,
          "notNull": true
        },
        "currency": {
          "name": "currency",
          "type": "text",
          "primaryKey": false,
          "notNull": true
        },
        "quotation_date": {
          "name": "quotation_date",
          "type": "timestamp",
          "primaryKey": false,
          "notNull": true
        },
        "status": {
          "name": "status",
          "type": "text",
          "primaryKey": false,
          "notNull": true
        },
        "decline_reason": {
          "name": "decline_reason",
          "type": "text",
          "primaryKey": false,
          "notNull": false
        },
        "notes": {
          "name": "notes",
          "type": "text",
          "primaryKey": false,
          "notNull": false
        },
        "requires_pre_condition_survey": {
          "name": "requires_pre_condition_survey",
          "type": "boolean",
          "primaryKey": false,
          "notNull": true,
          "default": false
        },
        "created_by": {
          "name": "created_by",
          "type": "serial",
          "primaryKey": false,
          "notNull": true
        },
        "last_updated": {
          "name": "last_updated",
          "type": "timestamp",
          "primaryKey": false,
          "notNull": true
        }
      },
      "indexes": {},
      "foreignKeys": {
        "quotations_created_by_users_id_fk": {
          "name": "quotations_created_by_users_id_fk",
          "tableFrom": "quotations",
          "tableTo": "users",
          "columnsFrom": [
            "created_by"
          ],
          "columnsTo": [
            "id"
          ],
          "onDelete": "no action",
          "onUpdate": "no action"
        }
      },
      "compositePrimaryKeys": {},
      "uniqueConstraints": {},
      "policies": {},
      "checkConstraints": {},
      "isRLSEnabled": false
    },
    "public.status_logs": {
      "name": "status_logs",
      "schema": "",
      "columns": {
        "id": {
          "name": "id",
          "type": "serial",
          "primaryKey": true,
          "notNull": true
        },
        "order_id": {
          "name": "order_id",
          "type": "serial",
          "primaryKey": false,
          "notNull": true
        },
        "statuses": {
          "name": "statuses",
          "type": "text[]",
          "primaryKey": false,
          "notNull": true
        },
        "timestamp": {
          "name": "timestamp",
          "type": "timestamp",
          "primaryKey": false,
          "notNull": true
        },
        "notes": {
          "name": "notes",
          "type": "text",
          "primaryKey": false,
          "notNull": false
        }
      },
      "indexes": {},
      "foreignKeys": {
        "status_logs_order_id_orders_id_fk": {
          "name": "status_logs_order_id_orders_id_fk",
          "tableFrom": "status_logs",
          "tableTo": "orders",
          "columnsFrom": [
            "order_id"
          ],
          "columnsTo": [
            "id"
          ],
          "onDelete": "no action",
          "onUpdate": "no action"
        }
      },
      "compositePrimaryKeys": {},
      "uniqueConstraints": {},
      "policies": {},
      "checkConstraints": {},
      "isRLSEnabled": false
    },
    "public.users": {
      "name": "users",
      "schema": "",
      "columns": {
        "id": {
          "name": "id",
          "type": "serial",
          "primaryKey": true,
          "notNull": true
        },
        "username": {
          "name": "username",
          "type": "text",
          "primaryKey": false,
          "notNull": true
        },
        "password": {
          "name": "password",
          "type": "text",
          "primaryKey": false,
          "notNull": true
        },
        "department": {
          "name": "department",
          "type": "text",
          "primaryKey": false,
          "notNull": true
        }
      },
      "indexes": {},
      "foreignKeys": {},
      "compositePrimaryKeys": {},
      "uniqueConstraints": {
        "users_username_unique": {
          "name": "users_username_unique",
          "nullsNotDistinct": false,
          "columns": [
            "username"
          ]
        }
      },
      "policies": {},
      "checkConstraints": {},
      "isRLSEnabled": false
    }
  },
  "enums": {},
  "schemas": {},
  "sequences": {},
  "roles": {},
  "policies": {},
  "views": {},
  "_meta": {
    "columns": {},
    "schemas": {},
    "tables": {}
  }
}